ospclientsdk/__init__.py
ospclientsdk/constants.py
ospclientsdk/exceptions.py
ospclientsdk/shell.py
ospclientsdk/helpers/__init__.py
ospclientsdk/helpers/context.py
ospclientsdk/helpers/decorators.py
ospclientsdk-0.5.0.dist-info/AUTHORS
ospclientsdk-0.5.0.dist-info/LICENSE
ospclientsdk-0.5.0.dist-info/METADATA
ospclientsdk-0.5.0.dist-info/WHEEL
ospclientsdk-0.5.0.dist-info/top_level.txt
ospclientsdk-0.5.0.dist-info/RECORD
