Metadata-Version: 2.1
Name: ospclientsdk
Version: 0.5.0
Summary: An SDK like wrapper around the openstackclient.
Home-page: https://github.com/Dannyb48/ospclientsdk
Author: Danny Baez
Author-email: danny.baez.jr@gmail.com
License: GPLv3
Platform: UNKNOWN
Classifier: Development Status :: 4 - Beta
Classifier: Intended Audience :: Developers
Classifier: Topic :: Software Development :: Quality Assurance
Classifier: Topic :: Software Development :: Libraries :: Python Modules
Classifier: Environment :: OpenStack
Classifier: Natural Language :: English
Classifier: License :: OSI Approved :: GNU General Public License v3 (GPLv3)
Classifier: Programming Language :: Python
Classifier: Programming Language :: Python :: 3.6
Requires-Dist: openstackclient
Requires-Dist: PyYaml
Provides-Extra: remote_shell
Requires-Dist: plumbum ; extra == 'remote_shell'
Provides-Extra: tripleo
Requires-Dist: python-tripleoclient ; extra == 'tripleo'
